LICENSE
README.md
openapi_schema/__init__.py
openapi_schema/generator.py
openapi_schema/py.typed
openapi_schema/schema.py
openapi_schema/serializers.py
openapi_schema/typing.py
openapi_schema/utils.py
openapi_schema/views.py
drf_openapi_schema-0.0.3.dist-info/LICENSE
drf_openapi_schema-0.0.3.dist-info/METADATA
drf_openapi_schema-0.0.3.dist-info/WHEEL
drf_openapi_schema-0.0.3.dist-info/RECORD
