Metadata-Version: 2.1
Name: drf-openapi-schema
Version: 0.0.3
Summary: Django Rest Framework OpenAPI Schema generation.
Home-page: https://mrthearman.github.io/drf-openapi-schema
License: MIT
Keywords: drf,django,rest_framework,rest,framework,openapi,schema,generator
Author: Matti Lamppu
Author-email: lamppu.matti.akseli@gmail.com
Requires-Python: >=3.9,<4
Classifier: Environment :: Web Environment
Classifier: Intended Audience :: Developers
Classifier: License :: OSI Approved :: MIT License
Classifier: Natural Language :: English
Classifier: Operating System :: OS Independent
Classifier: Programming Language :: Python
Classifier: Programming Language :: Python :: 3
Classifier: Programming Language :: Python :: 3.9
Classifier: Programming Language :: Python :: 3.10
Classifier: Programming Language :: Python :: 3.11
Classifier: Programming Language :: Python :: 3
Classifier: Programming Language :: Python :: 3 :: Only
Classifier: Programming Language :: Python :: 3.10
Classifier: Programming Language :: Python :: 3.11
Classifier: Programming Language :: Python :: 3.9
Provides-Extra: pydantic
Provides-Extra: uritemplate
Requires-Dist: Django (>=3.2)
Requires-Dist: PyYAML (>=6.0)
Requires-Dist: djangorestframework (>=3.12.0)
Requires-Dist: drf-serializer-inference (>=0.0.1)
Requires-Dist: pydantic (>=1.6.2) ; extra == "pydantic"
Requires-Dist: typing-extensions (>=4.4.0) ; python_version < "3.11"
Requires-Dist: uritemplate (>=4.1.1) ; extra == "uritemplate"
Project-URL: Bug Tracker, https://github.com/MrThearMan/drf-openapi-schema/issues
Project-URL: Repository, https://github.com/MrThearMan/drf-openapi-schema
